{
"type": "FeatureCollection",
"crs": { "type": "name", "properties": { "name": "urn:ogc:def:crs:OGC:1.3:CRS84" } },
"features": [
{ "type": "Feature", "properties": { "Port": "Tianjin, Beijing, China", "lat": 39.0850999, "lon": 117.19937 }, "geometry": { "type": "Point", "coordinates": [ 117.19937, 39.0850999 ] } },
{ "type": "Feature", "properties": { "Port": "Nagasaki City, Japan Nagasaki", "lat": 32.7503334, "lon": 129.8778888 }, "geometry": { "type": "Point", "coordinates": [ 129.8778888, 32.7503334 ] } },
{ "type": "Feature", "properties": { "Port": "Kagoshima City, Japan Kagoshima", "lat": 31.5968539, "lon": 130.5571392 }, "geometry": { "type": "Point", "coordinates": [ 130.5571392, 31.5968539 ] } },
{ "type": "Feature", "properties": { "Port": "Yokohama, Tokyo, Japan Kanagawa", "lat": 35.4436739, "lon": 139.6379639 }, "geometry": { "type": "Point", "coordinates": [ 139.637963899999988, 35.4436739 ] } },
{ "type": "Feature", "properties": { "Port": "Shimizu, Japan Shizuoka", "lat": 35.1132336, "lon": 138.4987208 }, "geometry": { "type": "Point", "coordinates": [ 138.4987208, 35.1132336 ] } },
{ "type": "Feature", "properties": { "Port": "Kobe-Osaka, Kyoto, Japan", "lat": 34.6937249, "lon": 135.5022535 }, "geometry": { "type": "Point", "coordinates": [ 135.5022535, 34.6937249 ] } },
{ "type": "Feature", "properties": { "Port": "Nha Trang, Vietnam", "lat": 12.2529152, "lon": 109.1899018 }, "geometry": { "type": "Point", "coordinates": [ 109.1899018, 12.2529152 ] } },
{ "type": "Feature", "properties": { "Port": "Saigon, Ho Chi Minh City, Vietnam", "lat": 10.8230989, "lon": 106.6296638 }, "geometry": { "type": "Point", "coordinates": [ 106.6296638, 10.8230989 ] } },
{ "type": "Feature", "properties": { "Port": "Singapore", "lat": 1.352083, "lon": 103.819836 }, "geometry": { "type": "Point", "coordinates": [ 103.819836, 1.352083 ] } }
]
}
